EdgeAccel/rtl/fusion_sb.sv
module fusion_sb #(
    parameter DATA_WIDTH = 16,
    parameter SEQ_LEN     = 16,
    parameter MEM_FILE    = "expected_output.mem"
)(
    input  logic                  clk,
    input  logic                  rst_n,
    input  logic                  valid,
    input  logic [DATA_WIDTH-1:0] kalman_out
);

    logic [DATA_WIDTH-1:0] golden_mem [0:SEQ_LEN-1];
    integer sample_count;
    logic [DATA_WIDTH-1:0] expected;

    initial begin
        $readmemh(MEM_FILE, golden_mem);
        $display("[SB] Loaded expected output from %s", MEM_FILE);
    end

    always_ff @(posedge clk) begin
        if (!rst_n) begin
            sample_count <= 0;
        end else if (valid) begin
            expected = golden_mem[sample_count];
            if (kalman_out !== expected) begin
                $display("[SB][ERROR] Sample %0d mismatch: Expected = %0d, Got = %0d",
                         sample_count, expected, kalman_out);
            end else begin
                $display("[SB][OK] Sample %0d matched: %0d", sample_count, kalman_out);
            end
            sample_count <= sample_count + 1;
        end
    end

endmodule

EdgeAccel/uvm/lidar_mon.sv
module lidar_mon (
  input  logic        clk,
  input  logic        rst_n,
  input  logic [15:0] lidar_data,
  input  logic        valid
);

  int sample_count;

  always_ff @(posedge clk or negedge rst_n) begin
    if (!rst_n) begin
      sample_count <= 0;
    end else if (valid) begin
      $display("[LiDAR MON] Time: %0t | Sample %0d | Data: %0d", $time, sample_count, lidar_data);
      sample_count <= sample_count + 1;
    end
  end

endmodule

EdgeAccel/rtl/imu_mon.sv
module imu_mon #(
    parameter DATA_WIDTH = 16,
    parameter SEQ_LEN = 16
)(
    input  logic                  clk,
    input  logic                  rst_n,
    input  logic [DATA_WIDTH-1:0] imu_data,
    input  logic                  valid
);

    int sample_count;

    // File output (optional logging)
    integer log_file;

    initial begin
        log_file = $fopen("imu_monitor_log.txt", "w");
    end

    always_ff @(posedge clk) begin
        if (!rst_n) begin
            sample_count <= 0;
        end else if (valid) begin
            sample_count++;
            $display("[IMU_MON] Sample %0d: imu_data = %0d", sample_count, imu_data);
            $fwrite(log_file, "%0d\n", imu_data);
        end
    end

    final begin
        $fclose(log_file);
        $display("[IMU_MON] Monitoring finished. %0d samples logged.", sample_count);
    end

endmodule

Week Wise File Directory/Week2/uvm/lidar_seq.sv
module lidar_seq #(
    parameter DATA_WIDTH = 16,
    parameter SEQ_LEN = 16
)(
    input  logic                  clk,
    input  logic                  rst_n,
    input  logic                  enable,
    output logic [DATA_WIDTH-1:0] lidar_data,
    output logic                  valid
);

    logic [$clog2(SEQ_LEN)-1:0] idx;

    always_ff @(posedge clk or negedge rst_n) begin
        if (!rst_n) begin
            idx        <= 0;
            valid      <= 0;
            lidar_data <= 0;
        end else if (enable) begin
            if (idx < SEQ_LEN) begin
                lidar_data <= 16'd120 + idx * 3;  // Example LiDAR pattern
                valid      <= 1;
                idx        <= idx + 1;
            end else begin
                valid <= 0;
            end
        end else begin
            valid <= 0;
        end
    end

endmodule

EdgeAccel/uvm/imu_seq.sv
module imu_seq #(
    parameter DATA_WIDTH = 16,
    parameter SEQ_LEN = 16
)(
    input  logic                  clk,
    input  logic                  rst_n,
    input  logic                  enable,
    output logic [DATA_WIDTH-1:0] imu_data,
    output logic                  valid
);

    logic [$clog2(SEQ_LEN)-1:0] idx;

    always_ff @(posedge clk or negedge rst_n) begin
        if (!rst_n) begin
            idx    <= 0;
            valid  <= 0;
            imu_data <= 0;
        end else if (enable) begin
            if (idx < SEQ_LEN) begin
                imu_data <= 16'd100 + idx * 2; // Synthetic IMU signal
                valid     <= 1;
                idx       <= idx + 1;
            end else begin
                valid <= 0;
            end
        end else begin
            valid <= 0;
        end
    end

endmodule

Week Wise File Directory/Week2/rtl/fusion_top.sv
module fusion_top (
  input  logic         clk,
  input  logic         rst_n,

  // AXI4-Lite interface
  input  logic [3:0]   s_axi_awaddr,
  input  logic         s_axi_awvalid,
  output logic         s_axi_awready,
  input  logic [31:0]  s_axi_wdata,
  input  logic [3:0]   s_axi_wstrb,
  input  logic         s_axi_wvalid,
  output logic         s_axi_wready,
  output logic [1:0]   s_axi_bresp,
  output logic         s_axi_bvalid,
  input  logic         s_axi_bready,
  input  logic [3:0]   s_axi_araddr,
  input  logic         s_axi_arvalid,
  output logic         s_axi_arready,
  output logic [31:0]  s_axi_rdata,
  output logic [1:0]   s_axi_rresp,
  output logic         s_axi_rvalid,
  input  logic         s_axi_rready,

  // Sensor interface
  input  logic [15:0]  imu_data,
  input  logic         imu_valid,
  input  logic [15:0]  lidar_data,
  input  logic         lidar_valid,

  // Kalman output
  output logic [15:0]  kalman_data,
  output logic         kalman_valid
);

  // ---------------------------------------------------------
  // AXI-lite register space
  // ---------------------------------------------------------
  typedef enum logic [3:0] {
    REG_IMU_ENABLE_ADDR   = 4'h0,
    REG_LIDAR_ENABLE_ADDR = 4'h4
  } reg_addr_t;

  logic imu_enable_reg, lidar_enable_reg;

  logic axi_awready_r, axi_wready_r, axi_bvalid_r;
  logic axi_arready_r, axi_rvalid_r;
  logic [31:0] axi_rdata_r;
  logic [1:0] axi_bresp_r, axi_rresp_r;

  assign s_axi_awready = axi_awready_r;
  assign s_axi_wready  = axi_wready_r;
  assign s_axi_bvalid  = axi_bvalid_r;
  assign s_axi_bresp   = axi_bresp_r;
  assign s_axi_arready = axi_arready_r;
  assign s_axi_rvalid  = axi_rvalid_r;
  assign s_axi_rdata   = axi_rdata_r;
  assign s_axi_rresp   = axi_rresp_r;

  // ---------------------------------------------------------
  // Write logic
  // ---------------------------------------------------------
  always_ff @(posedge clk) begin
    if (!rst_n) begin
      imu_enable_reg   <= 0;
      lidar_enable_reg <= 0;
      axi_awready_r    <= 0;
      axi_wready_r     <= 0;
      axi_bvalid_r     <= 0;
      axi_bresp_r      <= 2'b00;
    end else begin
      axi_awready_r <= s_axi_awvalid && !axi_awready_r;
      axi_wready_r  <= s_axi_wvalid && !axi_wready_r;

      if (axi_awready_r && s_axi_awvalid && axi_wready_r && s_axi_wvalid) begin
        case (s_axi_awaddr)
          REG_IMU_ENABLE_ADDR:   imu_enable_reg   <= s_axi_wdata[0];
          REG_LIDAR_ENABLE_ADDR: lidar_enable_reg <= s_axi_wdata[0];
        endcase
        axi_bvalid_r <= 1;
        axi_bresp_r  <= 2'b00;
      end else if (s_axi_bready) begin
        axi_bvalid_r <= 0;
      end
    end
  end

  // ---------------------------------------------------------
  // Read logic
  // ---------------------------------------------------------
  always_ff @(posedge clk) begin
    if (!rst_n) begin
      axi_arready_r <= 0;
      axi_rvalid_r  <= 0;
      axi_rdata_r   <= 0;
      axi_rresp_r   <= 2'b00;
    end else begin
      axi_arready_r <= s_axi_arvalid && !axi_arready_r;
      if (axi_arready_r && s_axi_arvalid) begin
        axi_rvalid_r <= 1;
        axi_rresp_r  <= 2'b00;
        case (s_axi_araddr)
          REG_IMU_ENABLE_ADDR:   axi_rdata_r <= imu_enable_reg;
          REG_LIDAR_ENABLE_ADDR: axi_rdata_r <= lidar_enable_reg;
          default:               axi_rdata_r <= 32'hDEADBEEF;
        endcase
      end else if (s_axi_rready) begin
        axi_rvalid_r <= 0;
      end
    end
  end

  // ---------------------------------------------------------
  // Connect to submodules (when implemented)
  // ---------------------------------------------------------
  logic [15:0] kalman_out;
  logic        kalman_out_valid;

  assign kalman_data  = kalman_out;
  assign kalman_valid = kalman_out_valid;

  // TODO: instantiate kalman_core and matrix_mult
  // and connect with imu/lidar gated by enable registers

endmodule

EdgeAccel/tb/tb_fusion.sv
`timescale 1ns/1ps

module tb_fusion;

  // Clock and reset
  logic clk;
  logic rst_n;

  // DUT inputs/outputs
  logic [15:0] imu_data, lidar_data;
  logic        imu_valid, lidar_valid;
  logic        kalman_valid;
  logic [15:0] kalman_out;

  // Stimulus control
  logic imu_enable, lidar_enable;

  // Clock generation
  always #5 clk = ~clk;

  // DUT instantiation
  fusion_top dut (
    .clk(clk),
    .rst_n(rst_n),
    .imu_data(imu_data),
    .imu_valid(imu_valid),
    .lidar_data(lidar_data),
    .lidar_valid(lidar_valid),
    .kalman_data(kalman_out),
    .kalman_valid(kalman_valid)
  );

  // IMU/LiDAR stimulus
  imu_seq imu_gen (
    .clk(clk),
    .rst_n(rst_n),
    .enable(imu_enable),
    .imu_data(imu_data),
    .valid(imu_valid)
  );

  lidar_seq lidar_gen (
    .clk(clk),
    .rst_n(rst_n),
    .enable(lidar_enable),
    .lidar_data(lidar_data),
    .valid(lidar_valid)
  );

  // Monitoring
  imu_mon imu_monitor (
    .clk(clk),
    .rst_n(rst_n),
    .imu_data(imu_data),
    .valid(imu_valid)
  );

  lidar_mon lidar_monitor (
    .clk(clk),
    .rst_n(rst_n),
    .lidar_data(lidar_data),
    .valid(lidar_valid)
  );

  // Scoreboard
  fusion_sb #(
    .DATA_WIDTH(16),
    .SEQ_LEN(16),
    .MEM_FILE("expected_output.mem")
  ) fusion_scoreboard (
    .clk(clk),
    .rst_n(rst_n),
    .valid(kalman_valid),
    .kalman_out(kalman_out)
  );

  // VCD dump
  initial begin
    $dumpfile("fusion_wave.vcd");
    $dumpvars(0, tb_fusion);
  end

  // Test sequence
  initial begin
    clk = 0;
    rst_n = 0;
    imu_enable = 0;
    lidar_enable = 0;
    #20;
    rst_n = 1;
    #20;
    imu_enable = 1;
    lidar_enable = 1;

    // Run simulation long enough to capture all output
    #1000;
    $display("Testbench completed.");
    $finish;
  end

initial begin
  $dumpfile("waveforms1/fusion_uvm.vcd");
  $dumpvars(0, tb_fusion);  // or fusion_test_top
end

endmodule

EdgeAccel/rtl/testing_fusion.sim/sim_1/behav/xsim/fusion_wave.vcd
$date
   Mon Sep  1 21:11:48 2025
$end

$version
  2024.2.0
  $dumpfile ("fusion_wave.vcd") 
$end

$timescale
  1ps
$end

$scope module tb_fusion $end
$var reg 1 ! clk $end
$var reg 1 " rst_n $end
$var reg 16 # imu_data [15:0] $end
$var reg 16 $ lidar_data [15:0] $end
$var reg 1 % imu_valid $end
$var reg 1 & lidar_valid $end
$var reg 1 ' kalman_valid $end
$var reg 16 ( kalman_out [15:0] $end
$var reg 1 ) imu_enable $end
$var reg 1 * lidar_enable $end
$scope module dut $end
$var wire 1 + clk $end
$var wire 1 , rst_n $end
$var wire 4 - s_axi_awaddr [3:0] $end
$var wire 1 . s_axi_awvalid $end
$var reg 1 / s_axi_awready $end
$var wire 32 0 s_axi_wdata [31:0] $end
$var wire 4 1 s_axi_wstrb [3:0] $end
$var wire 1 2 s_axi_wvalid $end
$var reg 1 3 s_axi_wready $end
$var reg 2 4 s_axi_bresp [1:0] $end
$var reg 1 5 s_axi_bvalid $end
$var wire 1 6 s_axi_bready $end
$var wire 4 7 s_axi_araddr [3:0] $end
$var wire 1 8 s_axi_arvalid $end
$var reg 1 9 s_axi_arready $end
$var reg 32 : s_axi_rdata [31:0] $end
$var reg 2 ; s_axi_rresp [1:0] $end
$var reg 1 < s_axi_rvalid $end
$var wire 1 = s_axi_rready $end
$var wire 16 > imu_data [15:0] $end
$var wire 1 ? imu_valid $end
$var wire 16 @ lidar_data [15:0] $end
$var wire 1 A lidar_valid $end
$var reg 16 ( kalman_data [15:0] $end
$var reg 1 ' kalman_valid $end
$var reg 1 B imu_enable_reg $end
$var reg 1 C lidar_enable_reg $end
$var reg 1 D axi_awready_r $end
$var reg 1 E axi_wready_r $end
$var reg 1 F axi_bvalid_r $end
$var reg 1 G axi_arready_r $end
$var reg 1 H axi_rvalid_r $end
$var reg 32 I axi_rdata_r [31:0] $end
$var reg 2 J axi_bresp_r [1:0] $end
$var reg 2 K axi_rresp_r [1:0] $end
$var reg 16 L kalman_out [15:0] $end
$var reg 1 M kalman_out_valid $end
$upscope $end
$scope module imu_gen $end
$var wire 1 N clk $end
$var wire 1 O rst_n $end
$var wire 1 P enable $end
$var reg 16 # imu_data [15:0] $end
$var reg 1 % valid $end
$var reg 4 Q idx [3:0] $end
$upscope $end
$scope module lidar_gen $end
$var wire 1 R clk $end
$var wire 1 S rst_n $end
$var wire 1 T enable $end
$var reg 16 $ lidar_data [15:0] $end
$var reg 1 & valid $end
$var reg 4 U idx [3:0] $end
$upscope $end
$scope module imu_monitor $end
$var wire 1 V clk $end
$var wire 1 W rst_n $end
$var wire 16 X imu_data [15:0] $end
$var wire 1 Y valid $end
$var reg 32 Z sample_count [31:0] $end
$var integer 32 [ log_file [31:0] $end
$upscope $end
$scope module lidar_monitor $end
$var wire 1 \ clk $end
$var wire 1 ] rst_n $end
$var wire 16 ^ lidar_data [15:0] $end
$var wire 1 _ valid $end
$var reg 32 ` sample_count [31:0] $end
$upscope $end
$scope module fusion_scoreboard $end
$var wire 1 a clk $end
$var wire 1 b rst_n $end
$var wire 1 c valid $end
$var wire 16 d kalman_out [15:0] $end
$var integer 32 e sample_count [31:0] $end
$var reg 16 f expected [15:0] $end
$upscope $end
$upscope $end
$enddefinitions $end

#0
$dumpvars
0!
0"
b0 #
b0 $
0%
0&
x'
bx (
0)
0*
0+
0,
bz -
z.
x/
bz 0
bz 1
z2
x3
bx 4
x5
z6
bz 7
z8
x9
bx :
bx ;
x<
z=
b0 >
0?
b0 @
0A
xB
xC
xD
xE
xF
xG
xH
bx I
bx J
bx K
bx L
xM
0N
0O
0P
b0 Q
0R
0S
0T
b0 U
0V
0W
b0 X
0Y
b0 Z
b11111111111111111011000111100000 [
0\
0]
b0 ^
0_
b0 `
0a
0b
xc
bx d
bx e
bx f
$end

#5000
1!
1+
0/
03
b0 4
05
09
b0 :
b0 ;
0<
0B
0C
0D
0E
0F
0G
0H
b0 I
b0 J
b0 K
1N
1R
1V
1\
1a
b0 e

#10000
0!
0+
0N
0R
0V
0\
0a

#15000
1!
1+
1N
1R
1V
1\
1a

#20000
0!
1"
0+
1,
0N
1O
0R
1S
0V
1W
0\
1]
0a
1b

#25000
1!
1+
x/
x3
x9
xD
xE
xG
1N
1R
1V
1\
1a

#30000
0!
0+
0N
0R
0V
0\
0a

#35000
1!
1+
1N
1R
1V
1\
1a

#40000
0!
1)
1*
0+
0N
1P
0R
1T
0V
0\
0a

#45000
1!
b1100100 #
b1111000 $
1%
1&
1+
b1100100 >
1?
b1111000 @
1A
1N
b1 Q
1R
b1 U
1V
b1100100 X
1Y
1\
b1111000 ^
1_
1a

#50000
0!
0+
0N
0R
0V
0\
0a

#55000
1!
b1100110 #
b1111011 $
1+
b1100110 >
b1111011 @
1N
b10 Q
1R
b10 U
1V
b1100110 X
b1 Z
1\
b1111011 ^
b1 `
1a

#60000
0!
0+
0N
0R
0V
0\
0a

#65000
1!
b1101000 #
b1111110 $
1+
b1101000 >
b1111110 @
1N
b11 Q
1R
b11 U
1V
b1101000 X
b10 Z
1\
b1111110 ^
b10 `
1a

#70000
0!
0+
0N
0R
0V
0\
0a

#75000
1!
b1101010 #
b10000001 $
1+
b1101010 >
b10000001 @
1N
b100 Q
1R
b100 U
1V
b1101010 X
b11 Z
1\
b10000001 ^
b11 `
1a

#80000
0!
0+
0N
0R
0V
0\
0a

#85000
1!
b1101100 #
b10000100 $
1+
b1101100 >
b10000100 @
1N
b101 Q
1R
b101 U
1V
b1101100 X
b100 Z
1\
b10000100 ^
b100 `
1a

#90000
0!
0+
0N
0R
0V
0\
0a

#95000
1!
b1101110 #
b10000111 $
1+
b1101110 >
b10000111 @
1N
b110 Q
1R
b110 U
1V
b1101110 X
b101 Z
1\
b10000111 ^
b101 `
1a

#100000
0!
0+
0N
0R
0V
0\
0a

#105000
1!
b1110000 #
b10001010 $
1+
b1110000 >
b10001010 @
1N
b111 Q
1R
b111 U
1V
b1110000 X
b110 Z
1\
b10001010 ^
b110 `
1a

#110000
0!
0+
0N
0R
0V
0\
0a

#115000
1!
b1110010 #
b10001101 $
1+
b1110010 >
b10001101 @
1N
b1000 Q
1R
b1000 U
1V
b1110010 X
b111 Z
1\
b10001101 ^
b111 `
1a

#120000
0!
0+
0N
0R
0V
0\
0a

#125000
1!
b1110100 #
b10010000 $
1+
b1110100 >
b10010000 @
1N
b1001 Q
1R
b1001 U
1V
b1110100 X
b1000 Z
1\
b10010000 ^
b1000 `
1a

#130000
0!
0+
0N
0R
0V
0\
0a

#135000
1!
b1110110 #
b10010011 $
1+
b1110110 >
b10010011 @
1N
b1010 Q
1R
b1010 U
1V
b1110110 X
b1001 Z
1\
b10010011 ^
b1001 `
1a

#140000
0!
0+
0N
0R
0V
0\
0a

#145000
1!
b1111000 #
b10010110 $
1+
b1111000 >
b10010110 @
1N
b1011 Q
1R
b1011 U
1V
b1111000 X
b1010 Z
1\
b10010110 ^
b1010 `
1a

#150000
0!
0+
0N
0R
0V
0\
0a

#155000
1!
b1111010 #
b10011001 $
1+
b1111010 >
b10011001 @
1N
b1100 Q
1R
b1100 U
1V
b1111010 X
b1011 Z
1\
b10011001 ^
b1011 `
1a

#160000
0!
0+
0N
0R
0V
0\
0a

#165000
1!
b1111100 #
b10011100 $
1+
b1111100 >
b10011100 @
1N
b1101 Q
1R
b1101 U
1V
b1111100 X
b1100 Z
1\
b10011100 ^
b1100 `
1a

#170000
0!
0+
0N
0R
0V
0\
0a

#175000
1!
b1111110 #
b10011111 $
1+
b1111110 >
b10011111 @
1N
b1110 Q
1R
b1110 U
1V
b1111110 X
b1101 Z
1\
b10011111 ^
b1101 `
1a

#180000
0!
0+
0N
0R
0V
0\
0a

#185000
1!
b10000000 #
b10100010 $
1+
b10000000 >
b10100010 @
1N
b1111 Q
1R
b1111 U
1V
b10000000 X
b1110 Z
1\
b10100010 ^
b1110 `
1a

#190000
0!
0+
0N
0R
0V
0\
0a

#195000
1!
b10000010 #
b10100101 $
1+
b10000010 >
b10100101 @
1N
b0 Q
1R
b0 U
1V
b10000010 X
b1111 Z
1\
b10100101 ^
b1111 `
1a

#200000
0!
0+
0N
0R
0V
0\
0a

#205000
1!
b1100100 #
b1111000 $
1+
b1100100 >
b1111000 @
1N
b1 Q
1R
b1 U
1V
b1100100 X
b10000 Z
1\
b1111000 ^
b10000 `
1a

#210000
0!
0+
0N
0R
0V
0\
0a

#215000
1!
b1100110 #
b1111011 $
1+
b1100110 >
b1111011 @
1N
b10 Q
1R
b10 U
1V
b1100110 X
b10001 Z
1\
b1111011 ^
b10001 `
1a

#220000
0!
0+
0N
0R
0V
0\
0a

#225000
1!
b1101000 #
b1111110 $
1+
b1101000 >
b1111110 @
1N
b11 Q
1R
b11 U
1V
b1101000 X
b10010 Z
1\
b1111110 ^
b10010 `
1a

#230000
0!
0+
0N
0R
0V
0\
0a

#235000
1!
b1101010 #
b10000001 $
1+
b1101010 >
b10000001 @
1N
b100 Q
1R
b100 U
1V
b1101010 X
b10011 Z
1\
b10000001 ^
b10011 `
1a

#240000
0!
0+
0N
0R
0V
0\
0a

#245000
1!
b1101100 #
b10000100 $
1+
b1101100 >
b10000100 @
1N
b101 Q
1R
b101 U
1V
b1101100 X
b10100 Z
1\
b10000100 ^
b10100 `
1a

#250000
0!
0+
0N
0R
0V
0\
0a

#255000
1!
b1101110 #
b10000111 $
1+
b1101110 >
b10000111 @
1N
b110 Q
1R
b110 U
1V
b1101110 X
b10101 Z
1\
b10000111 ^
b10101 `
1a

#260000
0!
0+
0N
0R
0V
0\
0a

#265000
1!
b1110000 #
b10001010 $
1+
b1110000 >
b10001010 @
1N
b111 Q
1R
b111 U
1V
b1110000 X
b10110 Z
1\
b10001010 ^
b10110 `
1a

#270000
0!
0+
0N
0R
0V
0\
0a

#275000
1!
b1110010 #
b10001101 $
1+
b1110010 >
b10001101 @
1N
b1000 Q
1R
b1000 U
1V
b1110010 X
b10111 Z
1\
b10001101 ^
b10111 `
1a

#280000
0!
0+
0N
0R
0V
0\
0a

#285000
1!
b1110100 #
b10010000 $
1+
b1110100 >
b10010000 @
1N
b1001 Q
1R
b1001 U
1V
b1110100 X
b11000 Z
1\
b10010000 ^
b11000 `
1a

#290000
0!
0+
0N
0R
0V
0\
0a

#295000
1!
b1110110 #
b10010011 $
1+
b1110110 >
b10010011 @
1N
b1010 Q
1R
b1010 U
1V
b1110110 X
b11001 Z
1\
b10010011 ^
b11001 `
1a

#300000
0!
0+
0N
0R
0V
0\
0a

#305000
1!
b1111000 #
b10010110 $
1+
b1111000 >
b10010110 @
1N
b1011 Q
1R
b1011 U
1V
b1111000 X
b11010 Z
1\
b10010110 ^
b11010 `
1a

#310000
0!
0+
0N
0R
0V
0\
0a

#315000
1!
b1111010 #
b10011001 $
1+
b1111010 >
b10011001 @
1N
b1100 Q
1R
b1100 U
1V
b1111010 X
b11011 Z
1\
b10011001 ^
b11011 `
1a

#320000
0!
0+
0N
0R
0V
0\
0a

#325000
1!
b1111100 #
b10011100 $
1+
b1111100 >
b10011100 @
1N
b1101 Q
1R
b1101 U
1V
b1111100 X
b11100 Z
1\
b10011100 ^
b11100 `
1a

#330000
0!
0+
0N
0R
0V
0\
0a

#335000
1!
b1111110 #
b10011111 $
1+
b1111110 >
b10011111 @
1N
b1110 Q
1R
b1110 U
1V
b1111110 X
b11101 Z
1\
b10011111 ^
b11101 `
1a

#340000
0!
0+
0N
0R
0V
0\
0a

#345000
1!
b10000000 #
b10100010 $
1+
b10000000 >
b10100010 @
1N
b1111 Q
1R
b1111 U
1V
b10000000 X
b11110 Z
1\
b10100010 ^
b11110 `
1a

#350000
0!
0+
0N
0R
0V
0\
0a

#355000
1!
b10000010 #
b10100101 $
1+
b10000010 >
b10100101 @
1N
b0 Q
1R
b0 U
1V
b10000010 X
b11111 Z
1\
b10100101 ^
b11111 `
1a

#360000
0!
0+
0N
0R
0V
0\
0a

#365000
1!
b1100100 #
b1111000 $
1+
b1100100 >
b1111000 @
1N
b1 Q
1R
b1 U
1V
b1100100 X
b100000 Z
1\
b1111000 ^
b100000 `
1a

#370000
0!
0+
0N
0R
0V
0\
0a

#375000
1!
b1100110 #
b1111011 $
1+
b1100110 >
b1111011 @
1N
b10 Q
1R
b10 U
1V
b1100110 X
b100001 Z
1\
b1111011 ^
b100001 `
1a

#380000
0!
0+
0N
0R
0V
0\
0a

#385000
1!
b1101000 #
b1111110 $
1+
b1101000 >
b1111110 @
1N
b11 Q
1R
b11 U
1V
b1101000 X
b100010 Z
1\
b1111110 ^
b100010 `
1a

#390000
0!
0+
0N
0R
0V
0\
0a

#395000
1!
b1101010 #
b10000001 $
1+
b1101010 >
b10000001 @
1N
b100 Q
1R
b100 U
1V
b1101010 X
b100011 Z
1\
b10000001 ^
b100011 `
1a

#400000
0!
0+
0N
0R
0V
0\
0a

#405000
1!
b1101100 #
b10000100 $
1+
b1101100 >
b10000100 @
1N
b101 Q
1R
b101 U
1V
b1101100 X
b100100 Z
1\
b10000100 ^
b100100 `
1a

#410000
0!
0+
0N
0R
0V
0\
0a

#415000
1!
b1101110 #
b10000111 $
1+
b1101110 >
b10000111 @
1N
b110 Q
1R
b110 U
1V
b1101110 X
b100101 Z
1\
b10000111 ^
b100101 `
1a

#420000
0!
0+
0N
0R
0V
0\
0a

#425000
1!
b1110000 #
b10001010 $
1+
b1110000 >
b10001010 @
1N
b111 Q
1R
b111 U
1V
b1110000 X
b100110 Z
1\
b10001010 ^
b100110 `
1a

#430000
0!
0+
0N
0R
0V
0\
0a

#435000
1!
b1110010 #
b10001101 $
1+
b1110010 >
b10001101 @
1N
b1000 Q
1R
b1000 U
1V
b1110010 X
b100111 Z
1\
b10001101 ^
b100111 `
1a

#440000
0!
0+
0N
0R
0V
0\
0a

#445000
1!
b1110100 #
b10010000 $
1+
b1110100 >
b10010000 @
1N
b1001 Q
1R
b1001 U
1V
b1110100 X
b101000 Z
1\
b10010000 ^
b101000 `
1a

#450000
0!
0+
0N
0R
0V
0\
0a

#455000
1!
b1110110 #
b10010011 $
1+
b1110110 >
b10010011 @
1N
b1010 Q
1R
b1010 U
1V
b1110110 X
b101001 Z
1\
b10010011 ^
b101001 `
1a

#460000
0!
0+
0N
0R
0V
0\
0a

#465000
1!
b1111000 #
b10010110 $
1+
b1111000 >
b10010110 @
1N
b1011 Q
1R
b1011 U
1V
b1111000 X
b101010 Z
1\
b10010110 ^
b101010 `
1a

#470000
0!
0+
0N
0R
0V
0\
0a

#475000
1!
b1111010 #
b10011001 $
1+
b1111010 >
b10011001 @
1N
b1100 Q
1R
b1100 U
1V
b1111010 X
b101011 Z
1\
b10011001 ^
b101011 `
1a

#480000
0!
0+
0N
0R
0V
0\
0a

#485000
1!
b1111100 #
b10011100 $
1+
b1111100 >
b10011100 @
1N
b1101 Q
1R
b1101 U
1V
b1111100 X
b101100 Z
1\
b10011100 ^
b101100 `
1a

#490000
0!
0+
0N
0R
0V
0\
0a

#495000
1!
b1111110 #
b10011111 $
1+
b1111110 >
b10011111 @
1N
b1110 Q
1R
b1110 U
1V
b1111110 X
b101101 Z
1\
b10011111 ^
b101101 `
1a

#500000
0!
0+
0N
0R
0V
0\
0a

#505000
1!
b10000000 #
b10100010 $
1+
b10000000 >
b10100010 @
1N
b1111 Q
1R
b1111 U
1V
b10000000 X
b101110 Z
1\
b10100010 ^
b101110 `
1a

#510000
0!
0+
0N
0R
0V
0\
0a

#515000
1!
b10000010 #
b10100101 $
1+
b10000010 >
b10100101 @
1N
b0 Q
1R
b0 U
1V
b10000010 X
b101111 Z
1\
b10100101 ^
b101111 `
1a

#520000
0!
0+
0N
0R
0V
0\
0a

#525000
1!
b1100100 #
b1111000 $
1+
b1100100 >
b1111000 @
1N
b1 Q
1R
b1 U
1V
b1100100 X
b110000 Z
1\
b1111000 ^
b110000 `
1a

#530000
0!
0+
0N
0R
0V
0\
0a

#535000
1!
b1100110 #
b1111011 $
1+
b1100110 >
b1111011 @
1N
b10 Q
1R
b10 U
1V
b1100110 X
b110001 Z
1\
b1111011 ^
b110001 `
1a

#540000
0!
0+
0N
0R
0V
0\
0a

#545000
1!
b1101000 #
b1111110 $
1+
b1101000 >
b1111110 @
1N
b11 Q
1R
b11 U
1V
b1101000 X
b110010 Z
1\
b1111110 ^
b110010 `
1a

#550000
0!
0+
0N
0R
0V
0\
0a

#555000
1!
b1101010 #
b10000001 $
1+
b1101010 >
b10000001 @
1N
b100 Q
1R
b100 U
1V
b1101010 X
b110011 Z
1\
b10000001 ^
b110011 `
1a

#560000
0!
0+
0N
0R
0V
0\
0a

#565000
1!
b1101100 #
b10000100 $
1+
b1101100 >
b10000100 @
1N
b101 Q
1R
b101 U
1V
b1101100 X
b110100 Z
1\
b10000100 ^
b110100 `
1a

#570000
0!
0+
0N
0R
0V
0\
0a

#575000
1!
b1101110 #
b10000111 $
1+
b1101110 >
b10000111 @
1N
b110 Q
1R
b110 U
1V
b1101110 X
b110101 Z
1\
b10000111 ^
b110101 `
1a

#580000
0!
0+
0N
0R
0V
0\
0a

#585000
1!
b1110000 #
b10001010 $
1+
b1110000 >
b10001010 @
1N
b111 Q
1R
b111 U
1V
b1110000 X
b110110 Z
1\
b10001010 ^
b110110 `
1a

#590000
0!
0+
0N
0R
0V
0\
0a

#595000
1!
b1110010 #
b10001101 $
1+
b1110010 >
b10001101 @
1N
b1000 Q
1R
b1000 U
1V
b1110010 X
b110111 Z
1\
b10001101 ^
b110111 `
1a

#600000
0!
0+
0N
0R
0V
0\
0a

#605000
1!
b1110100 #
b10010000 $
1+
b1110100 >
b10010000 @
1N
b1001 Q
1R
b1001 U
1V
b1110100 X
b111000 Z
1\
b10010000 ^
b111000 `
1a

#610000
0!
0+
0N
0R
0V
0\
0a

#615000
1!
b1110110 #
b10010011 $
1+
b1110110 >
b10010011 @
1N
b1010 Q
1R
b1010 U
1V
b1110110 X
b111001 Z
1\
b10010011 ^
b111001 `
1a

#620000
0!
0+
0N
0R
0V
0\
0a

#625000
1!
b1111000 #
b10010110 $
1+
b1111000 >
b10010110 @
1N
b1011 Q
1R
b1011 U
1V
b1111000 X
b111010 Z
1\
b10010110 ^
b111010 `
1a

#630000
0!
0+
0N
0R
0V
0\
0a

#635000
1!
b1111010 #
b10011001 $
1+
b1111010 >
b10011001 @
1N
b1100 Q
1R
b1100 U
1V
b1111010 X
b111011 Z
1\
b10011001 ^
b111011 `
1a

#640000
0!
0+
0N
0R
0V
0\
0a

#645000
1!
b1111100 #
b10011100 $
1+
b1111100 >
b10011100 @
1N
b1101 Q
1R
b1101 U
1V
b1111100 X
b111100 Z
1\
b10011100 ^
b111100 `
1a

#650000
0!
0+
0N
0R
0V
0\
0a

#655000
1!
b1111110 #
b10011111 $
1+
b1111110 >
b10011111 @
1N
b1110 Q
1R
b1110 U
1V
b1111110 X
b111101 Z
1\
b10011111 ^
b111101 `
1a

#660000
0!
0+
0N
0R
0V
0\
0a

#665000
1!
b10000000 #
b10100010 $
1+
b10000000 >
b10100010 @
1N
b1111 Q
1R
b1111 U
1V
b10000000 X
b111110 Z
1\
b10100010 ^
b111110 `
1a

#670000
0!
0+
0N
0R
0V
0\
0a

#675000
1!
b10000010 #
b10100101 $
1+
b10000010 >
b10100101 @
1N
b0 Q
1R
b0 U
1V
b10000010 X
b111111 Z
1\
b10100101 ^
b111111 `
1a

#680000
0!
0+
0N
0R
0V
0\
0a

#685000
1!
b1100100 #
b1111000 $
1+
b1100100 >
b1111000 @
1N
b1 Q
1R
b1 U
1V
b1100100 X
b1000000 Z
1\
b1111000 ^
b1000000 `
1a

#690000
0!
0+
0N
0R
0V
0\
0a

#695000
1!
b1100110 #
b1111011 $
1+
b1100110 >
b1111011 @
1N
b10 Q
1R
b10 U
1V
b1100110 X
b1000001 Z
1\
b1111011 ^
b1000001 `
1a

#700000
0!
0+
0N
0R
0V
0\
0a

#705000
1!
b1101000 #
b1111110 $
1+
b1101000 >
b1111110 @
1N
b11 Q
1R
b11 U
1V
b1101000 X
b1000010 Z
1\
b1111110 ^
b1000010 `
1a

#710000
0!
0+
0N
0R
0V
0\
0a

